{
  "user789" : {
    "userID" : "user789",
    "userName" : "Amr",
    "friendsIDs" : [ ],
    "blockedAccountsIDs" : [ ],
    "postsIDs" : [ ],
    "bio" : null,
    "hashedPassword" : "hashedPassword3",
    "status" : null,
    "email" : "amr@example.com",
    "dateOfBirth" : "1992-04-20",
    "profilePhotoPath" : null,
    "coverPhotoPath" : null,
    "storiesIDs" : [ ],
    "friendsREquest" : [ ],
    "id" : "user789"
  },
  "user123" : {
    "userID" : "user123",
    "userName" : "Ali Updated",
    "friendsIDs" : [ ],
    "blockedAccountsIDs" : [ ],
    "postsIDs" : [ ],
    "bio" : null,
    "hashedPassword" : "newHashedPassword",
    "status" : null,
    "email" : "ali.updated@example.com",
    "dateOfBirth" : "1990-05-15",
    "profilePhotoPath" : null,
    "coverPhotoPath" : null,
    "storiesIDs" : [ ],
    "friendsREquest" : [ ],
    "id" : "user123"
  }
}